{
    "color-case": "lower",
    "strip-spaces": true,
    "tab-size": 2,
    "element-case": "lower",
    "unitless-zero": true,
    "leading-zero": false,
    "color-shorthand": true,
    "sort-order": [
        ["$variable"],
        ["$include"],
        ["...", "$extend"],
        ["$import"],
        ["$include desktop", "$include desktop-tablet", "$include phone"]
    ],
    "sort-order-fallback": "abc",
    "vendor-prefix-align": false,
    "block-indent": 2,
    "always-semicolon": true,
    "space-before-colon": 0,
    "space-after-colon": 1,
    "space-before-opening-brace": 1,
    "space-after-opening-brace": "\n",
    "space-before-closing-brace": "\n",
    "space-before-selector-delimiter": "",
    "space-after-selector-delimiter": "\n",
    "space-between-declarations": "\n",
    "lines-between-rulesets": 1,
    "quotes": "single",
    "space-before-combinator": " ",
    "space-after-combinator": " ",
    "remove-empty-rulesets": true,
    "eof-newline": true
}
